testlinkmap/__init__.py
testlinkmap/__main__.py
testlinkmap/find_macho_linkmap.py
testlinkmap/utils/__init__.py
testlinkmap/utils/print_with_color.py
testlinkmap-1.0.1.4.dist-info/METADATA
testlinkmap-1.0.1.4.dist-info/WHEEL
testlinkmap-1.0.1.4.dist-info/top_level.txt
testlinkmap-1.0.1.4.dist-info/RECORD
