Metadata-Version: 2.1
Name: testlinkmap
Version: 1.0.1.4
Summary: find macho linkmap and output otool sections
Home-page: UNKNOWN
Author: LiTing
Author-email: match.lt@alibaba-inc.com
License: MIT
Keywords: linkmap macho python
Platform: UNKNOWN
Classifier: License :: OSI Approved :: MIT License
Classifier: Operating System :: OS Independent
Classifier: Programming Language :: Python :: 3
Classifier: Programming Language :: Python :: 3.6
Classifier: Programming Language :: Python :: 3.7
